{"2024-8":[{"title":"题解：牛客周赛 Round 56（A-E）","date":"2024-08-18T16:00:00.000Z","link":"/2024/08/19/题解：牛客周赛 Round 56（A-E）/"}],"2024-11":[{"title":"SCAU 高级程序设计语言 教材习题","date":"2024-11-10T16:00:00.000Z","link":"/2024/11/11/SCAU 高级程序设计语言 教材习题/"}],"2025-10":[{"title":"现在开始，还来得及","date":"2025-10-28T16:00:00.000Z","link":"/2025/10/29/top/"},{"title":"Fenwick 树状数组","date":"2025-10-28T16:00:00.000Z","link":"/2025/10/29/树状数组Fenwick/"}],"2025-11":[{"title":"数据库（MySQL）知识整理（更新ing）","date":"2025-11-22T16:00:00.000Z","link":"/2025/11/23/数据库（MySQL）知识整理/"}],"2025-12":[{"title":"C/C++IDE介绍之DevC++","date":"2025-12-03T18:04:20.000Z","link":"/2025/12/04/C_C++IDE介绍之DevC++/"},{"title":"哈尔滨CCPC前有感","date":"2025-12-05T06:06:44.000Z","link":"/2025/12/05/哈尔滨CCPC前有感/"},{"title":"C语言核心语法(1)：第一个C程序","date":"2025-12-09T07:39:44.000Z","link":"/2025/12/09/C语言核心语法(1)_第一个C程序/"}]}